llama_index/embeddings/anyscale/__init__.py
llama_index/embeddings/anyscale/base.py
llama_index/embeddings/anyscale/utils.py
llama_index_embeddings_anyscale-0.4.2.dist-info/METADATA
llama_index_embeddings_anyscale-0.4.2.dist-info/WHEEL
llama_index_embeddings_anyscale-0.4.2.dist-info/licenses/LICENSE
llama_index_embeddings_anyscale-0.4.2.dist-info/RECORD
