Metadata-Version: 2.4
Name: llama-index-embeddings-anyscale
Version: 0.4.2
Summary: llama-index embeddings anyscale integration
Author-email: Your Name <you@example.com>
License-Expression: MIT
License-File: LICENSE
Requires-Python: <4.0,>=3.9
Requires-Dist: llama-index-core<0.15,>=0.14.3
Requires-Dist: llama-index-embeddings-openai<0.6,>=0.5.0
Requires-Dist: llama-index-llms-openai<0.7,>=0.6.0
